{
    "model_path":  "models/BitNet-b1.58-2B-4T/ggml-model-i2_s.gguf",
    "server_host":  "127.0.0.1",
    "server_port":  8765,
    "context_size":  4096,
    "threads":  8,
    "gpu_layers":  99,
    "temperature":  0.7,
    "max_tokens":  512,
    "system_prompt":  "You are EmberOS, an AI agent layer running on this Windows machine. You can observe system context (active window, clipboard), execute tools, manage files, run shell commands, and assist the user with any task. Be concise, practical, and proactive.",
    "memory_db_path":  "data/ember.db",
    "vector_store_path":  "data/vectors",
    "sentence_transformer_cache":  "data/models/sentence_transformer",
    "max_context_tokens":  3500,
    "summarize_after_turns":  10,
    "turns_to_keep_verbatim":  6,
    "max_total_conversations":  10000,
    "log_file":  "logs/emberos.log",
    "service_name":  "EmberOSAgent",
    "tray_autostart":  true,
    "gpu_mode":  "cuda",
    "quant_type":  "i2_s",
    "agent_api_port":  8766
}
